dicomsort/__init__.py
dicomsort/core.py
dicomsort/folderprocessing.py
dicomsort/mappers.py
dicomsort/parser.py
trialbureautools/__init__.py
trialbureautools/permissions.py
trialbureautools/cli/__init__.py
trialbureautools/cli/dicomsort.py
trialbureautools/cli/main.py
trialbureautools/cli/permissions.py
trialbureautools-0.3.13.dist-info/AUTHORS.rst
trialbureautools-0.3.13.dist-info/LICENSE
trialbureautools-0.3.13.dist-info/METADATA
trialbureautools-0.3.13.dist-info/WHEEL
trialbureautools-0.3.13.dist-info/entry_points.txt
trialbureautools-0.3.13.dist-info/top_level.txt
trialbureautools-0.3.13.dist-info/RECORD
