Metadata-Version: 2.1
Name: trialbureautools
Version: 0.3.13
Summary: Command line utilities for the radboudumc trial bureau
Home-page: https://github.com/sjoerdk/trialbureautools
Author: Sjoerd Kerkstra
Author-email: sjoerd.kerkstra@radboudumc.nl
License: MIT license
Keywords: trialbureautools
Classifier: Development Status :: 2 - Pre-Alpha
Classifier: Intended Audience :: Developers
Classifier: License :: OSI Approved :: MIT License
Classifier: Natural Language :: English
Classifier: Programming Language :: Python :: 3.6
License-File: LICENSE
License-File: AUTHORS.rst
Requires-Dist: Click >=6.0
Requires-Dist: icaclswrap
Requires-Dist: pydicom
Requires-Dist: lark-parser
Requires-Dist: pyaml
